LICENSE
regta/__init__.py
regta/__main__.py
regta/console.py
regta/enums.py
regta/exceptions.py
regta/jobs.py
regta/logging.py
regta/schedulers.py
regta/templates/class_job.template
regta/templates/decorator_job.template
regta/templates.py
regta/utils.py
regta-0.3.0.dist-info/LICENSE
regta-0.3.0.dist-info/WHEEL
regta-0.3.0.dist-info/entry_points.txt
regta-0.3.0.dist-info/METADATA
regta-0.3.0.dist-info/RECORD
