Metadata-Version: 2.1
Name: regta
Version: 0.3.0
Summary: Production-ready scheduler with async, multithreading and multiprocessing support.
Home-page: https://regta.alinsky.tech
License: MIT
Keywords: scheduler,multithreading,multiprocessing,async,jobs,tasks,cron,periodic,regular
Author: Vladimir Alinsky
Author-email: Vladimir@Alinsky.tech
Requires-Python: >=3.7.2,<4.0.0
Classifier: Development Status :: 5 - Production/Stable
Classifier: Environment :: Console
Classifier: Framework :: AsyncIO
Classifier: License :: OSI Approved :: MIT License
Classifier: Programming Language :: Python :: 3
Classifier: Programming Language :: Python :: 3.8
Classifier: Programming Language :: Python :: 3.9
Classifier: Programming Language :: Python :: 3.10
Classifier: Programming Language :: Python :: 3.11
Classifier: Programming Language :: Python :: 3.10
Classifier: Programming Language :: Python :: 3.11
Classifier: Programming Language :: Python :: 3.7
Classifier: Programming Language :: Python :: 3.8
Classifier: Programming Language :: Python :: 3.9
Requires-Dist: Jinja2 (>=3.1.2,<4.0.0)
Requires-Dist: asyncio (>=3.4.3,<4.0.0)
Requires-Dist: click (>=8.1.3,<9.0.0)
Requires-Dist: regta-period (>=0.2.0,<0.3.0)
Project-URL: Repository, https://github.com/SKY-ALIN/regta
